arkhn_arx/__init__.py
arkhn_arx/main_arx.py
arkhn_arx-0.0.8.dist-info/LICENSE
arkhn_arx-0.0.8.dist-info/METADATA
arkhn_arx-0.0.8.dist-info/WHEEL
arkhn_arx-0.0.8.dist-info/top_level.txt
arkhn_arx-0.0.8.dist-info/RECORD
