Metadata-Version: 2.1
Name: arkhn-arx
Version: 0.0.8
Summary: arkhn_arx is a tool to pseudonymize or anonymize datasets while evaluating reidentification risk metrics
Home-page: https://github.com/arkhn/pyarxaas
Author: Celine Thiriez
Author-email: contact@arkhn.com
License: MIT License
Download-URL: https://github.com/arkhn/pyarxaas/archive/0.0.1.tar.gz
Keywords: arkhn,dataset anonymization,dataset pseudonymization,reidentification risk evaluation
Platform: UNKNOWN
Classifier: Development Status :: 3 - Alpha
Classifier: Intended Audience :: Developers
Classifier: Topic :: Software Development :: Build Tools
Classifier: Programming Language :: Python :: 3
Classifier: Programming Language :: Python :: 3.4
Classifier: Programming Language :: Python :: 3.5
Classifier: Programming Language :: Python :: 3.6
Classifier: Programming Language :: Python :: 3.7
Requires-Dist: certifi (==2020.4.5.1)
Requires-Dist: chardet (==3.0.4)
Requires-Dist: idna (==2.9)
Requires-Dist: numpy (==1.18.4)
Requires-Dist: pandas (==1.0.1)
Requires-Dist: pyARXaaS (==0.5.7)
Requires-Dist: python-dateutil (==2.8.1)
Requires-Dist: pytz (==2020.1)
Requires-Dist: requests (==2.23.0)
Requires-Dist: six (==1.15.0)
Requires-Dist: uplink (==0.9.0)
Requires-Dist: uritemplate (==3.0.1)
Requires-Dist: urllib3 (==1.25.9)
